csvdivider/__init__.py
csvdivider/cli.py
csvdivider/csv_divider.py
csvdivider-1.4.1.dist-info/LICENSE
csvdivider-1.4.1.dist-info/METADATA
csvdivider-1.4.1.dist-info/WHEEL
csvdivider-1.4.1.dist-info/entry_points.txt
csvdivider-1.4.1.dist-info/top_level.txt
csvdivider-1.4.1.dist-info/RECORD
