Metadata-Version: 2.1
Name: csvdivider
Version: 1.4.1
Summary: csvdivider
Home-page: https://github.com/AlexNg9527/csvdivider.git
Author: Alex Ng
Author-email: alex_q_wu@qq.com
Maintainer: Alex Ng
Maintainer-email: alex_q_wu@qq.com
License: MIT
Platform: UNKNOWN
Classifier: Programming Language :: Python :: 3
License-File: LICENSE
